interactive_gym/__init__.py
interactive_gym/configurations/__init__.py
interactive_gym/configurations/configuration_constants.py
interactive_gym/configurations/experiment_config.py
interactive_gym/configurations/object_contexts.py
interactive_gym/configurations/remote_config.py
interactive_gym/configurations/render_configs.py
interactive_gym/scenes/__init__.py
interactive_gym/scenes/gym_scene.py
interactive_gym/scenes/scene.py
interactive_gym/scenes/stager.py
interactive_gym/scenes/static_scene.py
interactive_gym/scenes/unity_scene.py
interactive_gym/scenes/utils.py
interactive_gym/server/__init__.py
interactive_gym/server/app.py
interactive_gym/server/callback.py
interactive_gym/server/game_manager.py
interactive_gym/server/player_pairing_manager.py
interactive_gym/server/pyodide_game_coordinator.py
interactive_gym/server/remote_game.py
interactive_gym/server/server_app.py
interactive_gym/server/server_game_runner.py
interactive_gym/server/utils.py
interactive_gym/utils/__init__.py
interactive_gym/utils/inference_utils.py
interactive_gym/utils/onnx_inference_utils.py
interactive_gym/utils/typing.py
interactive_gym-0.1.1.dist-info/LICENSE
interactive_gym-0.1.1.dist-info/METADATA
interactive_gym-0.1.1.dist-info/WHEEL
interactive_gym-0.1.1.dist-info/top_level.txt
interactive_gym-0.1.1.dist-info/RECORD
