Metadata-Version: 2.1
Name: interactive-gym
Version: 0.1.1
Summary: A platform for running interactive experiments in the browser with standard simulation environments.
Author: Chase McDonald
Author-email: chasecmcdonald@gmail.com
License-File: LICENSE
Requires-Dist: numpy
Provides-Extra: server
Requires-Dist: eventlet ; extra == 'server'
Requires-Dist: flask ; extra == 'server'
Requires-Dist: flask-socketio ; extra == 'server'
Requires-Dist: msgpack ; extra == 'server'
Requires-Dist: pandas ; extra == 'server'
Requires-Dist: flatten-dict ; extra == 'server'
